drel/__init__.py
drel/utils.py
drel/core/__init__.py
drel/core/builders.py
drel/core/config.py
drel/core/es.py
drel/core/models.py
drel/core/schemas.py
drel/core/utils.py
drel/django/__init__.py
drel/django/api.py
drel/requests/__init__.py
drel/requests/api.py
tests/__init__.py
tests/conftest.py
tests/test_requests.py
tests/test_schemas.py
tests/test_django/__init__.py
tests/test_django/test_api.py
drel-0.5.1.dist-info/LICENSE
drel-0.5.1.dist-info/METADATA
drel-0.5.1.dist-info/WHEEL
drel-0.5.1.dist-info/top_level.txt
drel-0.5.1.dist-info/RECORD
