Metadata-Version: 2.1
Name: drel
Version: 0.5.1
Summary: Django request ElasticSearch logging
Home-page: https://github.com/potykion/drel
Author: Leybovich Nikita
Author-email: potykion@gmail.com
License: UNKNOWN
Platform: UNKNOWN
Classifier: Programming Language :: Python :: 3
Classifier: License :: OSI Approved :: MIT License
Classifier: Operating System :: OS Independent
Requires-Dist: django (>=1.11)
Requires-Dist: requests (>=2.18.0)
Requires-Dist: elasticsearch (<7.0.0,>=6.0.0)
Requires-Dist: marshmallow (<3.0.0,>=2.16.0)
Requires-Dist: attrs (>=18.1.0)
